README.rst
setup.py
satapi/__init__.py
satapi/hostgroups.py
satapi/hosts.py
satapi/version.py
satapi.egg-info/PKG-INFO
satapi.egg-info/SOURCES.txt
satapi.egg-info/dependency_links.txt
satapi.egg-info/not-zip-safe
satapi.egg-info/requires.txt
satapi.egg-info/top_level.txt