Metadata-Version: 1.1
Name: satapi
Version: 0.2.0
Summary: Satellite 6 API REST module
Home-page: http://github.com/soukron/satapi2
Author: Sergio G.
Author-email: soukron@gmbros.net
License: GPLv3
Platform: UNKNOWN
Classifier: Development Status :: 4 - Beta
Classifier: Intended Audience :: Developers
Classifier: License :: OSI Approved :: GNU General Public License v3 (GPLv3)
Classifier: Operating System :: OS Independent
Classifier: Programming Language :: Python
Classifier: Topic :: Software Development :: Libraries
